dodotable_xlsx.py
dodotable_xlsx-0.4.1.dist-info/METADATA
dodotable_xlsx-0.4.1.dist-info/WHEEL
dodotable_xlsx-0.4.1.dist-info/top_level.txt
dodotable_xlsx-0.4.1.dist-info/RECORD
