Metadata-Version: 2.1
Name: dodotable-xlsx
Version: 0.4.1
Summary: Excel (.xlsx) exporter for dodotable
Home-page: https://github.com/spoqa/dodotable-xlsx
Author: Hong Minhee
Author-email: hongminhee@spoqa.com
License: MIT license
Platform: UNKNOWN
Requires-Dist: dodotable (<1.0.0,>=0.4.0)
Requires-Dist: MarkupSafe
Requires-Dist: XlsxWriter (<1.0.0,>=0.9.6)
